examples/__init__.py
examples/echo_bot.py
examples/host_monitor_by_user.py
examples/host_watch_bot.py
examples/overload_bot.py
examples/simplest.py
examples/test_fwk.py
plugin_system/__init__.py
plugin_system/main.py
plugin_system/plugin_base.py
plugin_system/plugin_manager.py
plugin_system/plugins/__init__.py
plugin_system/plugins/example_plugin.py
tlgfwk/__init__.py
tlgfwk/handlers.py
tlgfwk/tlgfwk.py
tlgfwk/examples/__init__.py
tlgfwk/examples/echo_bot.py
tlgfwk/examples/host_monitor_by_user.py
tlgfwk/examples/host_watch_bot.py
tlgfwk/examples/overload_bot.py
tlgfwk/examples/simplest.py
tlgfwk/examples/test_fwk.py
tlgfwk/plugin_system/__init__.py
tlgfwk/plugin_system/main.py
tlgfwk/plugin_system/plugin_base.py
tlgfwk/plugin_system/plugin_manager.py
tlgfwk/plugin_system/plugins/__init__.py
tlgfwk/plugin_system/plugins/example_plugin.py
tlgfwk/translations/__init__.py
tlgfwk/translations/translations.py
tlgfwk/util/__init__.py
tlgfwk/util/test_util_watch.py
tlgfwk/util/util_balance.py
tlgfwk/util/util_config.py
tlgfwk/util/util_console.py
tlgfwk/util/util_decorators.py
tlgfwk/util/util_env.py
tlgfwk/util/util_log.py
tlgfwk/util/util_paypal_receive.py
tlgfwk/util/util_stripe.py
tlgfwk/util/util_stripe_link.py
tlgfwk/util/util_telegram.py
tlgfwk/util/util_watch.py
util/__init__.py
util/test_util_watch.py
util/util_balance.py
util/util_config.py
util/util_console.py
util/util_decorators.py
util/util_env.py
util/util_log.py
util/util_paypal_receive.py
util/util_stripe.py
util/util_stripe_link.py
util/util_telegram.py
util/util_watch.py
tlgfwk-1.0.8.dist-info/LICENSE
tlgfwk-1.0.8.dist-info/METADATA
tlgfwk-1.0.8.dist-info/WHEEL
tlgfwk-1.0.8.dist-info/top_level.txt
tlgfwk-1.0.8.dist-info/RECORD
